arith_mr_sagar/___init___.py
arith_mr_sagar/arith.py
arith_mr_sagar-0.0.5.dist-info/licenses/License
arith_mr_sagar-0.0.5.dist-info/METADATA
arith_mr_sagar-0.0.5.dist-info/WHEEL
arith_mr_sagar-0.0.5.dist-info/top_level.txt
arith_mr_sagar-0.0.5.dist-info/RECORD
