Metadata-Version: 2.4
Name: arith-mr-sagar
Version: 0.0.5
Summary: A simple arithmetic package example
Author-email: "Mr. Sagar" <sagartallapogu711@gmail.com>
License: MIT License
Classifier: Programming Language :: Python :: 3
Classifier: License :: OSI Approved :: MIT License
Classifier: Operating System :: OS Independent
Requires-Python: >=3.7
License-File: License
Dynamic: license-file
